{
	"description": "A WePY project",
	"setting": {
		"urlCheck": false,
		"es6": false,
		"postcss": false,
		"preloadBackgroundData": false,
		"minified": false,
		"newFeature": true,
		"coverView": true,
		"autoAudits": false,
		"showShadowRootInWxmlPanel": true,
		"scopeDataCheck": false,
		"checkInvalidKey": true,
		"checkSiteMap": true,
		"uploadWithSourceMap": true,
		"babelSetting": {
			"ignore": [],
			"disablePlugins": [],
			"outputPath": ""
		}
	},
	"compileType": "miniprogram",
	"appid": "wxb5e5a265b4e089e9",
	"projectname": "weapp",
	"miniprogramRoot": "weapp/",
	"simulatorType": "wechat",
	"simulatorPluginLibVersion": {},
	"condition": {}
}